MANIFEST.in
README.md
setup.cfg
setup.py
github2pypi/__init__.py
github2pypi/replace_url.py
logboard/__init__.py
logboard/parser.py
logboard/views.py
logboard.egg-info/PKG-INFO
logboard.egg-info/SOURCES.txt
logboard.egg-info/dependency_links.txt
logboard.egg-info/entry_points.txt
logboard.egg-info/requires.txt
logboard.egg-info/top_level.txt
logboard/cli/__init__.py
logboard/cli/logboard.py
logboard/cli/logtable.py
logboard/templates/index.html